hyper/__init__.py
hyper/certs.pem
hyper/cli.py
hyper/compat.py
hyper/contrib.py
hyper/httplib_compat.py
hyper/ssl_compat.py
hyper/tls.py
hyper/common/__init__.py
hyper/common/bufsocket.py
hyper/common/connection.py
hyper/common/decoder.py
hyper/common/exceptions.py
hyper/common/headers.py
hyper/common/util.py
hyper/http11/__init__.py
hyper/http11/connection.py
hyper/http11/parser.py
hyper/http11/response.py
hyper/http20/__init__.py
hyper/http20/connection.py
hyper/http20/errors.py
hyper/http20/exceptions.py
hyper/http20/response.py
hyper/http20/stream.py
hyper/http20/util.py
hyper/http20/window.py
hyper_qta-1.1.1.data/data/requirements.txt
hyper_qta-1.1.1.data/data/version.txt
hyper_qta-1.1.1.dist-info/LICENSE
hyper_qta-1.1.1.dist-info/METADATA
hyper_qta-1.1.1.dist-info/NOTICES
hyper_qta-1.1.1.dist-info/WHEEL
hyper_qta-1.1.1.dist-info/entry_points.txt
hyper_qta-1.1.1.dist-info/top_level.txt
hyper_qta-1.1.1.dist-info/RECORD
