Metadata-Version: 2.1
Name: hyper-qta
Version: 1.1.1
Summary: HTTP/2 Client for Python
Home-page: http://hyper.rtfd.org
Author: qta
License: MIT License
Classifier: Development Status :: 3 - Alpha
Classifier: Intended Audience :: Developers
Classifier: License :: OSI Approved :: MIT License
Classifier: Programming Language :: Python
Classifier: Programming Language :: Python :: 2
Classifier: Programming Language :: Python :: 2.7
Classifier: Programming Language :: Python :: 3
Classifier: Programming Language :: Python :: 3.5
Classifier: Programming Language :: Python :: 3.6
Classifier: Programming Language :: Python :: Implementation :: CPython
License-File: LICENSE
License-File: NOTICES
Requires-Dist: rfc3986<2.0,>=1.1.0
Requires-Dist: brotlipy<1.0,>=0.7.0
Requires-Dist: six
Requires-Dist: cryptography<1.0; platform_python_implementation == "PyPy" and python_full_version < "2.7.9"
Requires-Dist: pyOpenSSL>=0.15; python_full_version < "2.7.9"
Requires-Dist: service-identity>=14.0.0; python_full_version < "2.7.9"
Requires-Dist: h2!=2.5.0,<3.0,>=2.4; python_version < "3.10"
Requires-Dist: hyperframe<4.0,>=3.2; python_version < "3.10"
Requires-Dist: cffi==1.12.3; python_version < "3.9"
Requires-Dist: enum34<2,>=1.0.4; python_version == "2.7" or python_version == "3.3"
Requires-Dist: cffi==1.14.4; python_version == "3.9"
Requires-Dist: cffi==1.16.0; python_version >= "3.10"
Requires-Dist: h2==3.2.0; python_version >= "3.10"
Requires-Dist: hyperframe<6,>=5.2.0; python_version >= "3.10"
Provides-Extra: fast
Requires-Dist: pycohttpparser; extra == "fast"
